HISTORY.txt
MANIFEST.in
README.txt
bootstrap.py
buildout.cfg
setup.cfg
setup.py
collective/__init__.py
collective.portlet.collectionbysubject.egg-info/PKG-INFO
collective.portlet.collectionbysubject.egg-info/SOURCES.txt
collective.portlet.collectionbysubject.egg-info/dependency_links.txt
collective.portlet.collectionbysubject.egg-info/entry_points.txt
collective.portlet.collectionbysubject.egg-info/namespace_packages.txt
collective.portlet.collectionbysubject.egg-info/not-zip-safe
collective.portlet.collectionbysubject.egg-info/requires.txt
collective.portlet.collectionbysubject.egg-info/top_level.txt
collective/portlet/__init__.py
collective/portlet/collectionbysubject/__init__.py
collective/portlet/collectionbysubject/collectionbysubject.pt
collective/portlet/collectionbysubject/collectionbysubject.py
collective/portlet/collectionbysubject/collectionbysubject_view.pt
collective/portlet/collectionbysubject/config.py
collective/portlet/collectionbysubject/configure.zcml
collective/portlet/collectionbysubject/version.txt
collective/portlet/collectionbysubject/locales/collective.portlet.collectionbysubject.pot
collective/portlet/collectionbysubject/profiles/default/metadata.xml
collective/portlet/collectionbysubject/profiles/default/portlets.xml
collective/portlet/collectionbysubject/tests/__init__.py
collective/portlet/collectionbysubject/tests/base.py
collective/portlet/collectionbysubject/tests/test_portlet.py
docs/INSTALL.txt
docs/LICENSE.GPL
docs/LICENSE.txt