Metadata-Version: 1.0
Name: collective.portlet.collectionbysubject
Version: 0.3
Summary: Portlet that groups collection items by subject
Home-page: http://
Author: Rok Garbas
Author-email: rok@garbas.si
License: GPL
Keywords: zope plone portlet collective collection grouping
Platform: UNKNOWN
Classifier: Framework :: Plone
Classifier: Programming Language :: Python
Classifier: Topic :: Software Development :: Libraries :: Python Modules
